gptconsole.py
gptconsole-0.12.dist-info/LICENSE
gptconsole-0.12.dist-info/METADATA
gptconsole-0.12.dist-info/WHEEL
gptconsole-0.12.dist-info/entry_points.txt
gptconsole-0.12.dist-info/top_level.txt
gptconsole-0.12.dist-info/RECORD
